[
    {
        "id":"web_design_principle",
        "title": "Web Design Principles",
        "description":"Tips for creating a good looking website",
        "reminder":"Please note that some part this article is based on and summarized from a <a href='https://www.youtube.com/watch?v=A8bsrYqn0NQ'>YouTube video</a>",
        "author": "<a href='https://khian.netlify.app/'>Khian Victory D. Calderon</a>",
        "fullContent": "<b>5 Web Design Principles:</b><br/> <ul> <li><u><i>Balance</i></u><br/> This refers to the distribution of visual weight within a design. It can be symmetrical (evenly distributed) or asymmetrical (unevenly distributed but still visually balanced). The goal is to create a sense of equilibrium that is pleasing to the eye. </li><br/> <li><u><i>Alignment</i></u><br/> This principle involves arranging elements so they line up with each other or with the overall design grid. Proper alignment helps create a sense of order and organization, guiding the viewer's eye through the design. </li><br/> <li><u><i>Proximity</i></u><br/> Proximity refers to placing related items close to each other. This helps to create a visual relationship between elements, making it easier for viewers to understand how different parts of the design are related. </li><br/> <li><u><i>Repetition</i></u><br/> Repetition involves using similar elements throughout a design to create consistency and unity. This can include repeating colors, shapes, fonts, or patterns to tie the design together and reinforce a cohesive look. </li><br/> <li><u><i>Contrast</i></u><br/> Contrast is the difference between elements in a design, such as color, size, or shape. It helps to highlight important information, create visual interest, and guide the viewer’s attention to key areas of the design. </li><br/> </ul> <b>Other tips in web designing:</b><br/> <ul> <li><u><i>User Experience Tips</i></u><br/> <ul> <li><b>Prioritize Mobile Responsiveness</b><br/> Ensure your site is optimized for mobile devices, as a significant portion of users will access it via smartphones or tablets. </li><br/> <li><b>Fast Load Times</b><br/> Optimize images, use efficient coding practices, and leverage caching to ensure your site loads quickly. Fast load times improve user experience and can positively impact SEO. </li><br/> <li><b>Intuitive Navigation</b><br/> Design a clear, straightforward navigation system. Use familiar patterns and place important links in easily accessible locations. </li><br/> <li><b>Accessible Design</b><br/> Follow accessibility guidelines (like WCAG) to ensure your site is usable by people with disabilities. This includes proper contrast, text alternatives for images, and keyboard navigability. </li><br/> <li><b>Clear Calls to Action (CTAs)</b><br/> Make your CTAs prominent and persuasive. Use action-oriented language and ensure they stand out visually. </li><br/> </ul> </li><br/> <li><u><i>Visual Design Tips</i></u><br/> <ul> <li><b>Consistent Branding</b><br/> Use consistent colors, fonts, and imagery that align with your brand’s identity. This helps create a cohesive and professional look. </li><br/> <li><b>White Space</b><br/> Don't overcrowd your design. Adequate white space improves readability and focuses attention on key elements. </li><br/> <li><b>Typography</b><br/> Choose readable fonts and establish a hierarchy with different font sizes and weights. Limit the number of fonts used to maintain visual coherence. </li><br/> <li><b>Visual Hierarchy</b><br/> Organize content with a clear hierarchy to guide users' attention. Use size, color, and placement to emphasize important elements. </li><br/> <li><b>Imagery</b><br/> Use high-quality images that support your content. Avoid stock photos that look generic and aim for images that resonate with your audience. </li><br/> </ul> </li><br/> <li><u><i>Content Tips</i></u><br/> <ul> <li><b>Engaging Content</b><br/> Write compelling, relevant content that speaks to your target audience. Use headings, bullet points, and short paragraphs to enhance readability. </li><br/> <li><b>SEO Best Practices</b><br/> Optimize your content for search engines with relevant keywords, meta tags, and descriptive URLs. This helps improve your site's visibility in search results. </li><br/> <li><b>Regular Updates</b><br/> Keep your content fresh and up-to-date. Regular updates can boost user engagement and improve search engine rankings. </li><br/> <li><b>User Feedback</b><br/> Incorporate feedback from users to continuously improve your design. Tools like surveys and usability testing can provide valuable insights. </li><br/> </ul> </li><br/> <li><u><i>Technical Tips</i></u><br/> <ul> <li><b>Cross-Browser Compatibility</b><br/> Test your site across different browsers and devices to ensure it functions correctly everywhere. </li><br/> <li><b>Security</b><br/> Implement security measures like SSL certificates and secure authentication to protect user data and build trust. </li><br/> <li><b>Analytics</b><br/> Use tools like Google Analytics to track user behavior and gather insights on how your site is performing. This data can inform future design improvements. </li><br/> <li><b>Clean Code</b><br/> Write clean, well-organized code to improve site performance and make it easier to maintain and update. </li><br/> </ul> </li><br/> </ul>"
    },
    {
        "id":"mlm_dark_side",
        "title": "Dark Side of MLM",
        "description":"Uncover the dark side of networking / MLM or multi-level marketing",
        "author": "Anonymous",
        "fullContent": "<i>Multi-level marketing (MLM)</i> has gained notoriety for its controversial practices and potential pitfalls, shedding light on several darker aspects within the industry.<br/><br/> <ul> <li><b>High Attrition Rates:</b> MLM companies often experience high turnover rates among distributors. Many participants invest time and money but end up leaving without achieving substantial financial returns. The business model relies heavily on recruiting new members to replace those who drop out.</li><br/> <li><b>Misleading Income Promises:</b> MLM companies frequently promote the potential for lucrative earnings, showcasing top earners as examples of success. However, these earnings are often not representative of the average participant's experience. Many distributors find themselves earning little to no profit after factoring in expenses like product purchases, training fees, and marketing materials.</li><br/> <li><b>Product Overpricing and Quality Concerns:</b> Products sold through MLMs can be criticized for being overpriced compared to similar items available in retail stores. There are also concerns about product quality, as the emphasis may be more on recruitment than on product development or consumer satisfaction.</li><br/> <li><b>Emphasis on Recruitment:</b> MLMs often prioritize recruiting new distributors over selling products. Participants are encouraged to build their <u>downline</u> by recruiting others into the business. This can lead to market saturation and intense competition among distributors within the same network.</li><br/> <li><b>Complex Compensation Structures:</b> Compensation plans in MLMs can be complex and difficult to understand. They often reward recruiting and building a large network of distributors rather than actual retail sales. This focus on recruitment can overshadow genuine product distribution.</li><br/> <li><b>Legal and Regulatory Issues:</b> MLMs have faced legal scrutiny and regulatory challenges in various countries due to concerns about deceptive practices, pyramid schemes, and violations of consumer protection laws. Some MLM companies have been fined or shut down for operating illegal pyramid schemes disguised as legitimate business opportunities.</li><br/> <li><b>Social and Personal Relationships:</b> Joining an MLM can strain personal relationships as distributors may feel pressured to recruit friends and family members. This pressure can lead to tension and conflict if individuals are not interested in or skeptical of the business opportunity.</li><br/> <li><b>Psychological Impact:</b> Participants in MLMs may experience psychological stress from financial losses, unmet expectations, or feeling misled by promises of easy success. The pressure to maintain positivity and recruit new members can also create emotional strain.</li><br/> </ul><br/> <i>While some individuals may find success in MLMs, the industry's structure and practices have raised ethical concerns and skepticism. Prospective participants are advised to conduct thorough research, consider potential risks, and assess whether the business model aligns with their financial goals and ethical values before joining.</i>"
    },
    {
        "id":"korean_drama_addiction",
        "title": "K-Drama Addiction",
        "description":"Why so many people are so addicted to watching korean drama movies?",
        "author": "Anonymous",
        "fullContent": "\"<b>Korean drama addiction</b> has surged in popularity globally, captivating audiences with its unique storytelling, compelling characters, and emotional depth.<br/> Originating from <u>South Korea</u>, K-dramas have transcended cultural boundaries, becoming a significant part of the global entertainment landscape.<br/> What sets K-dramas apart are their diverse genres, including: <ul> <li><i>Romantic comedies</i></li> <li><i>Historical dramas</i></li> <li><i>Thrillers</i></li> <li><i>Fantasy series</i></li> </ul> Each genre offers a distinct blend of cultural insights, complex narratives, and nuanced performances.<br/><br/> One of the key draws of K-dramas lies in their ability to evoke <b>powerful emotions</b> and create <i>immersive storytelling experiences</i>.<br/> Viewers often find themselves deeply invested in the lives of characters, rooting for their relationships, overcoming challenges, and witnessing personal growth.<br/> This emotional engagement is enhanced by meticulous attention to detail in production, including: <ul> <li><i>Stunning cinematography</i></li> <li><i>Elaborate costumes</i></li> <li><i>Evocative soundtracks</i></li> </ul> that complement each storyline.<br/><br/> Binge-watching has become a common phenomenon among K-drama enthusiasts, driven by the <b>addictive nature</b> of these series.<br/> Many fans find themselves glued to their screens, consuming multiple episodes in a single sitting to: <ul> <li><i>Unravel plot twists</i></li> <li><i>Understand character motivations</i></li> <li><i>Experience the highs and lows of each narrative arc</i></li> </ul> This binge-watching culture has been facilitated by <u>streaming platforms</u> that offer convenient access to a vast library of K-dramas.<br/><br/> Another factor contributing to K-drama addiction is their <b>diverse themes</b> and <b>universal appeal</b>.<br/> While romance remains a staple, K-dramas also explore: <ul> <li><i>Social issues</i></li> <li><i>Family dynamics</i></li> <li><i>Identity struggles</i></li> <li><i>Historical events</i></li> </ul> offering viewers a deeper understanding of Korean culture and societal values.<br/><br/> Beyond entertainment, K-dramas have also influenced: <ul> <li><b>Fashion trends</b> – Viewers are inspired by character styles, leading to trends in clothing, accessories, and beauty products.</li> <li><b>Tourism</b> – Popular filming locations in South Korea have seen an increase in visitors seeking to experience the settings firsthand.</li> <li><b>Language learning</b> – The widespread availability of subtitles encourages language learners to immerse themselves in Korean dialogue.</li> </ul> Social media has played a pivotal role in the <b>global spread</b> of K-drama addiction, providing platforms for fans to: <ul> <li><i>Connect and share their love for favorite series</i></li> <li><i>Discuss plot developments</i></li> <li><i>Create fan art and fanfiction</i></li> </ul> Online communities have formed around specific dramas, fostering a sense of <u>community</u> among international viewers.<br/><br/> <b>In conclusion</b>, K-drama addiction is fueled by its <i>compelling storytelling, emotional resonance, cultural richness, and global accessibility</i>.<br/> As their popularity continues to grow worldwide, K-dramas serve not only as a form of entertainment but also as a <u>gateway</u> to understanding Korean culture, fostering cross-cultural appreciation and connection among diverse audiences.<br/> \""
    },
    {
        "id":"great_listener",
        "title": "A Great Listener",
        "description":"Being a good listener is better than a great speaker",
        "author": "Anonymous",
        "fullContent": "\"Being a <b>good listener</b> is often considered more valuable than being a great speaker for several reasons:<br/><br/> <u>Understanding:</u> <i>Effective listening fosters deeper understanding of others' perspectives, feelings, and needs.</i><br/><br/> <u>Building Relationships:</u> <i>Listening attentively strengthens relationships by showing respect, empathy, and interest in others.</i><br/><br/> <u>Conflict Resolution:</u> <i>Listening reduces misunderstandings and facilitates constructive communication, essential for resolving conflicts.</i><br/><br/> <u>Learning:</u> <i>Listening allows for learning from others' experiences, knowledge, and viewpoints, promoting personal growth.</i><br/><br/> <u>Empowerment:</u> <i>Being heard and understood empowers individuals to express themselves openly and feel valued.</i><br/><br/> <u>Effective Communication:</u> <i>Good listeners are better able to respond thoughtfully, communicate clearly, and convey empathy.</i><br/><br/> <u>Leadership:</u> <i>Effective leaders prioritize listening to their team members, fostering trust, collaboration, and innovation.</i><br/><br/> <b>While speaking skills are valuable, the ability to listen actively and empathetically is essential for meaningful connections, collaboration, and personal development.</b>\""
    },
    {
        "id":"college_struggle",
        "title": "College Struggles",
        "description":"Know the different struggles in college in every aspect",
        "reminder":"This article may be based on a real-life experience of a college student",
        "author": "Anonymous",
        "fullContent": "\"College life presents various challenges and struggles for students as they navigate academic, social, and personal responsibilities:<br/><br/> <ul> <li><b>Academic Pressure:</b> Balancing coursework, assignments, exams, and deadlines can be overwhelming, especially with challenging classes and high academic expectations.</li><br/> <li><b>Time Management:</b> Juggling classes, studying, part-time jobs, extracurricular activities, and personal commitments requires effective time management skills.</li><br/> <li><b>Financial Stress:</b> Managing tuition fees, student loans, living expenses, and budgeting can cause financial strain and anxiety.</li><br/> <li><b>Social Adjustments:</b> Adapting to a new social environment, making friends, and dealing with peer pressure or loneliness can impact mental well-being.</li><br/> <li><b>Homesickness:</b> Missing family and hometown comforts while adjusting to living away from home can be emotionally challenging.</li><br/> <li><b>Mental Health:</b> Coping with stress, anxiety, depression, or academic pressure while maintaining mental well-being is crucial but often overlooked.</li><br/> <li><b>Career Uncertainty:</b> Deciding on a major, career path, internships, and post-graduation plans can create uncertainty and indecision.</li><br/> <li><b>Balancing Responsibilities:</b> Finding a balance between academics, extracurricular activities, work, social life, and personal health can be demanding.</li><br/> <li><b>Cultural Adjustment:</b> <i>International students</i> may face additional challenges related to <u>cultural differences</u>, language barriers, and adapting to a new educational system.</li><br/> <li><b>Lack of Support:</b> Feeling isolated or lacking adequate support from peers, professors, or campus resources can exacerbate difficulties.</li> </ul><br/> <i>Overcoming these challenges often involves seeking support from campus resources, developing resilience, prioritizing self-care, and establishing a healthy balance between academic and personal life.</i>\""
    },
    {
        "id":"adulting",
        "title": "Adulting",
        "description":"From teenager to adult, there are a lot of responsibilities and changes in ourselves",
        "author": "Anonymous",
        "fullContent": "Financial responsibility evolves as you transition from <u>teenager</u> to <u>adult</u>, encompassing several key stages:<br/><br/> <b>Teenager:</b><br/> <ul> <li><b>Education:</b> Focus on academic achievements and consider part-time jobs or internships for personal development and savings.</li> <li><b>Savings:</b> Start cultivating saving habits by setting aside a portion of any earnings or allowances.</li> <li><b>Budgeting:</b> Learn basic budgeting skills to manage personal expenses and understand the value of money.</li> <li><b>Financial Literacy:</b> Educate yourself on financial concepts such as savings, interest, and responsible spending.</li> </ul><br/> <b>Youth/Young Adult:</b><br/> <ul> <li><b>Income:</b> Establish a stable income through full-time employment, freelance work, or entrepreneurial ventures.</li> <li><b>Expenses:</b> Create and stick to a realistic budget that covers living expenses, savings, debt repayment, and discretionary spending.</li> <li><b>Savings and Investments:</b> Build an emergency fund and explore long-term investments such as retirement accounts or stocks.</li> <li><b>Debt Management:</b> Handle any student loans, credit card debts, or other financial obligations responsibly.</li> </ul><br/> <b>Adulting/Established Adult:</b><br/> <ul> <li><b>Financial Goals:</b> Set and prioritize financial goals like buying a home, starting a family, or planning for retirement.</li> <li><b>Insurance:</b> Obtain necessary insurance coverage (e.g., health, life, property) to protect against unexpected financial burdens.</li> <li><b>Estate Planning:</b> Consider creating a will and establishing directives for future financial and healthcare decisions.</li> <li><b>Continued Learning:</b> Stay informed about financial trends, tax implications, and investment opportunities to optimize financial stability and growth.</li> </ul><br/> <i>Transitioning from teenage years to adulthood involves acquiring financial knowledge, practicing disciplined saving and spending habits, and adapting to evolving financial responsibilities for long-term security and success.</i>"
    },
    {
        "id":"healthy_relationship",
        "title": "Healthy Relationship",
        "description":"No relationship is perfect, but there is healthy one",
        "author": "Anonymous",
        "fullContent": "\"Building a <u>near-perfect relationship</u> involves several key factors:<br/><br/> <ul> <li><b>Communication:</b> <i>Open and honest communication</i> is essential for understanding each other's needs, emotions, and expectations.</li><br/> <li><b>Trust:</b> <i>Trust forms the foundation</i> of a strong relationship. It's built through reliability, honesty, and consistency in actions and words.</li><br/> <li><b>Respect:</b> <i>Mutual respect</i> involves valuing each other's opinions, boundaries, and individuality. It fosters a supportive and positive environment.</li><br/> <li><b>Empathy:</b> Being <i>empathetic</i> means understanding and sharing your partner's feelings, perspectives, and experiences, enhancing emotional connection.</li><br/> <li><b>Compromise:</b> Healthy relationships require <i>flexibility and compromise</i> to resolve conflicts and accommodate each other's needs and differences.</li><br/> <li><b>Quality Time:</b> Spending <i>meaningful time</i> together strengthens bonds and creates shared experiences, nurturing intimacy and connection.</li><br/> <li><b>Appreciation:</b> Expressing <i>gratitude and acknowledgment</i> of each other's efforts and qualities reinforces positivity and strengthens the relationship.</li><br/> <li><b>Growth Together:</b> Supporting each other's <i>personal growth and goals</i> while evolving as a couple contributes to long-term happiness and fulfillment.</li><br/> </ul> <i>While no relationship is perfect</i>, nurturing these qualities can help cultivate a strong, fulfilling, and <u>near-perfect partnership</u>. \""
    },
    {
        "id":"business_guide",
        "title": "Business Guide",
        "description":"A general guide tip on how to start a traditional business",
        "author": "Anonymous",
        "fullContent": "\"Starting and becoming successful in business can be divided into three key parts: <b>planning</b>, <b>managing</b>, and <b>achieving success</b>.<br/><br/> <b>1. Planning:</b><br/><br/> <ul> <li><u>Idea Development:</u> Identify a unique business idea based on market research and personal interests or expertise.</li> <li><u>Market Analysis:</u> Research your target market, competitors, and industry trends to assess demand and potential challenges.</li> <li><u>Business Plan:</u> Create a detailed business plan outlining your goals, strategies, financial projections, and operational plans.</li> <li><u>Legal and Financial Setup:</u> Choose a legal structure, register your business, obtain necessary licenses, and secure funding.</li> </ul><br/> <b>2. Managing:</b><br/><br/> <ul> <li><u>Operations:</u> Establish efficient processes for production, inventory management, and customer service.</li> <li><u>Financial Management:</u> Monitor cash flow, expenses, and revenue to ensure financial stability and growth.</li> <li><u>Team Building:</u> Hire skilled employees or partners who complement your strengths and share your business vision.</li> <li><u>Marketing and Sales:</u> Develop effective marketing strategies to promote your brand, attract customers, and drive sales.</li> </ul><br/> <b>3. Becoming Successful:</b><br/><br/> <ul> <li><u>Adaptability:</u> Stay flexible and responsive to market changes, customer feedback, and industry trends.</li> <li><u>Innovation:</u> Continuously innovate products, services, or processes to maintain a competitive edge.</li> <li><u>Customer Focus:</u> Prioritize customer satisfaction and build strong relationships to foster loyalty and repeat business.</li> <li><u>Evaluate and Adjust:</u> Regularly assess business performance, identify areas for improvement, and make strategic adjustments.</li> <li><u>Long-Term Vision:</u> Maintain a clear vision for growth and sustainability, setting achievable goals and milestones.</li> </ul><br/> By focusing on <i>thorough planning</i>, <i>effective management</i>, and <i>strategic actions towards success</i>, you can navigate the challenges of starting and growing a successful business.\""
    },
    {
        "id":"ai_usage",
        "title": "AI Usage",
        "description":"What are the pros and cons effects of using artificial intelligence?",
        "author": "Anonymous",
        "fullContent": "\"Artificial Intelligence (<b>AI</b>) offers various advantages and disadvantages, shaping its impact on society and technology:<br/><br/> <b>Pros:</b><br/> <ul> <li><u>Automation:</u> <i>AI automates repetitive tasks, improving efficiency and reducing human error.</i></li> <li><u>Decision Making:</u> <i>AI analyzes large datasets quickly, aiding in decision-making processes across industries.</i></li> <li><u>Innovation:</u> <i>AI fuels innovation in fields like healthcare, finance, and transportation, enabling new discoveries and advancements.</i></li> <li><u>Personalization:</u> <i>AI algorithms personalize user experiences, recommending content and products based on preferences and behaviors.</i></li> <li><u>Accessibility:</u> <i>AI enhances accessibility through applications like speech recognition and translation services.</i></li> <li><u>Safety:</u> <i>AI improves safety in autonomous vehicles, surveillance systems, and disaster response scenarios.</i></li> </ul><br/> <b>Cons:</b><br/> <ul> <li><u>Job Displacement:</u> <i>AI automation may replace jobs, leading to unemployment and economic disruption.</i></li> <li><u>Privacy Concerns:</u> <i>AI collects and analyzes vast amounts of personal data, raising concerns about privacy and data security.</i></li> <li><u>Bias and Fairness:</u> <i>AI algorithms can exhibit biases, reflecting societal prejudices and impacting fairness in decision-making.</i></li> <li><u>Dependency:</u> <i>Over-reliance on AI systems may lead to vulnerabilities and disruptions if systems fail or are manipulated.</i></li> <li><u>Ethical Dilemmas:</u> <i>AI raises ethical concerns about accountability, transparency, and the use of AI in sensitive applications like criminal justice.</i></li> <li><u>Human Interaction:</u> <i>Increased AI adoption may reduce human interaction and empathy in customer service and interpersonal relationships.</i></li> </ul><br/> Overall, while <b>AI</b> offers significant benefits in <b>automation, decision-making, and innovation</b>, careful consideration of its <u>societal, ethical, and economic impacts</u> is essential to harness its potential responsibly.\""
    },
    {
        "id":"dangerous_cooking_oil",
        "title": "Dangers of cooking oil",
        "description":"Discover the various dangerous effects of using cooking oil in everyday food",
        "author": "Anonymous",
        "fullContent": "\"Cooking oil, while an essential ingredient in food preparation, can be dangerous due to several factors related to its use, handling, and disposal. Understanding these risks can help individuals make safer choices in the kitchen and minimize negative environmental and health impacts.<br/><br/> <u><b>Fire Hazards in the Kitchen</b></u><br/> One of the primary dangers of cooking oil is its potential to cause kitchen fires. When oil is heated to high temperatures, it reaches its <i>smoke point</i>—the temperature at which it starts to break down and emit smoke. If the oil continues to heat beyond this point, it can ignite and cause a grease fire, which can be extremely difficult to extinguish with water. Adding water to burning oil can cause violent splattering, spreading the fire and increasing the risk of burns or severe property damage.<br/><br/> To prevent such incidents, it is crucial to:<br/> <ul> <li>Use a thermometer to monitor the oil temperature when deep frying.</li> <li>Never leave hot oil unattended, as it can quickly overheat.</li> <li>Keep a lid or fire extinguisher nearby to smother potential fires.</li> <li>Avoid overheating oil beyond its recommended cooking temperature.</li> </ul> Additionally, oil splatters can cause burns, particularly if moisture or wet food is introduced suddenly into hot oil. Wearing protective clothing and using proper cooking techniques, such as gently lowering food into the oil, can help minimize risks.<br/><br/> <u><b>Environmental Impact of Improper Disposal</b></u><br/> Improper disposal of cooking oil is another significant concern. Many people mistakenly pour used oil down the drain, leading to clogged pipes and sewer blockages. When oil cools, it solidifies and sticks to the inner walls of pipes, eventually restricting water flow and leading to costly plumbing repairs. On a larger scale, improper disposal contributes to <i>fatbergs</i>—massive accumulations of fat, oil, and grease that clog sewage systems, requiring extensive efforts to remove.<br/><br/> When cooking oil enters waterways, it forms a thick layer on the surface, reducing oxygen levels and harming aquatic ecosystems. Marine and freshwater organisms can suffer from reduced oxygen, leading to suffocation and disruptions in the food chain.<br/><br/> To dispose of cooking oil responsibly:<br/> <ul> <li>Let the oil cool completely before handling.</li> <li>Use a sealed container to store used oil before proper disposal.</li> <li>Take oil to designated recycling centers, where it can be repurposed for biodiesel or other uses.</li> <li>Check local regulations for waste disposal guidelines.</li> </ul> Some cities and municipalities offer collection programs for used cooking oil, ensuring it is repurposed sustainably rather than contributing to environmental pollution.<br/><br/> <u><b>Health Risks of Excessive Consumption</b></u><br/> The type and quantity of cooking oil consumed can significantly impact overall health. While oils are necessary for cooking and provide essential fatty acids, excessive consumption, particularly of oils high in saturated and trans fats, can lead to obesity, heart disease, and high cholesterol.<br/><br/> Oils such as palm oil and hydrogenated vegetable oils contain high levels of unhealthy fats, which can contribute to plaque buildup in arteries, increasing the risk of cardiovascular diseases. On the other hand, healthier options such as olive oil, canola oil, and avocado oil contain monounsaturated and polyunsaturated fats, which have been linked to improved heart health.<br/><br/> To maintain a balanced diet:<br/> <ul> <li>Use oils in moderation, even healthy ones, as they are calorie-dense.</li> <li>Choose oils with healthier fat profiles, such as extra virgin olive oil, which contains antioxidants and anti-inflammatory properties.</li> <li>Limit deep-fried foods, opting for baking, grilling, or steaming instead.</li> </ul> By making informed choices about cooking oils, individuals can enjoy flavorful meals while promoting long-term health.<br/><br/> <u><b>Sustainable and Safe Practices</b></u><br/> To mitigate the dangers associated with cooking oil, it is essential to:<br/> <ul> <li>Store oil in proper containers, away from heat and direct sunlight, to prevent it from becoming rancid.</li> <li>Reuse oil safely, filtering it after each use and avoiding excessive reheating, which can degrade its quality.</li> <li>Dispose of oil responsibly, using recycling programs or designated waste disposal methods.</li> <li>Consider alternatives, such as air frying or using non-stick cookware, to reduce reliance on excessive oil in cooking.</li> </ul> Additionally, repurposing used cooking oil for biodiesel production can be an environmentally friendly solution, reducing reliance on fossil fuels and promoting sustainability. Some businesses and households participate in programs that collect used oil for conversion into biofuels, contributing to a greener future.<br/><br/> <u><b>Conclusion</b></u><br/> Cooking oil plays a vital role in meal preparation, but its improper use and disposal can lead to serious safety, environmental, and health issues. By understanding these risks and taking necessary precautions, individuals can ensure safer cooking practices, reduce environmental harm, and maintain a healthier lifestyle. Whether through proper storage, mindful consumption, or responsible disposal, small efforts can make a big difference in promoting safety and sustainability.\""
    },
    {
        "id":"work_for_money",
        "title": "Work for Money",
        "description":"Rich don't work for money, money works for them and it is one of the rich's secret",
        "author": "Anonymous",
        "fullContent": "The concept that <b>\"the rich don't work for money\"</b> challenges traditional notions of wealth accumulation and financial independence. <br/><br/>Coined in personal finance literature and popularized by <i>Robert Kiyosaki</i> in his book <b>\"Rich Dad Poor Dad\"</b>, this idea suggests that true wealth is not primarily generated through conventional employment, but rather through assets, investments, and passive income streams. <br/><br/> According to this philosophy: <ul> <li>Individuals who focus solely on earning a paycheck are limited by trading their time for money.</li> <li>The wealthy prioritize building and acquiring income-generating assets such as <i>real estate, stocks, businesses, or intellectual property</i>.</li> <li>These assets generate <b>passive income</b>, which continues to flow regardless of active work.</li> </ul> Proponents of this mindset argue that relying solely on earned income can perpetuate a cycle of financial dependence and limited growth. <br/><br/>By contrast, investing in assets that <i>appreciate in value</i> or <i>produce ongoing income</i> allows individuals to accumulate wealth and achieve financial freedom over time. <br/><br/> The principle of <b>\"the rich don't work for money\"</b> emphasizes: <ul> <li><u>Financial education</u> and <u>strategic investment decisions</u>.</li> <li>Thinking beyond traditional employment.</li> <li>Long-term wealth-building strategies for financial security and independence.</li> </ul> While controversial and often debated, this concept has influenced many to rethink their approach to personal finance and wealth management. <br/><br/>It encourages individuals to cultivate a mindset focused on: <ul> <li>Building assets.</li> <li>Generating passive income.</li> <li>Moving beyond reliance on earned wages or salaries.</li> </ul> Ultimately, whether one subscribes to this philosophy or not, it underscores the broader idea that <b>financial success</b> requires: <ul> <li><i>Strategic planning.</i></li> <li><i>Investment in income-producing assets.</i></li> <li><i>A proactive approach to managing one's financial future.</i></li> </ul> As such, the notion that <b>\"the rich don't work for money\"</b> serves as a <u>provocative reminder</u> to consider alternative paths to wealth creation and financial independence, challenging conventional wisdom and prompting individuals to explore new opportunities for lasting prosperity."
    }
]